optim_cy/optim.cp39-win_amd64.pyd
optim_cy/optim.cpp
optim_cy/optim.cpython-38-x86_64-linux-gnu.so
optim_cy/optim.cpython-39-x86_64-linux-gnu.so
rotspy/__init__.py
rotspy/__main__.py
rotspy/calculateOverlaps1.py
rotspy/calculateOverlaps2.py
rotspy/helpers.py
rotspy/plot_rots.py
rotspy/rots.py
rots_py-1.4.0.dist-info/LICENSE
rots_py-1.4.0.dist-info/METADATA
rots_py-1.4.0.dist-info/WHEEL
rots_py-1.4.0.dist-info/entry_points.txt
rots_py-1.4.0.dist-info/top_level.txt
rots_py-1.4.0.dist-info/RECORD
