Metadata-Version: 2.1
Name: rots-py
Version: 1.4.0
Summary: ROTS gene ranking implementation in Python
Author-email: "F.Mamadbekov, M.Shakya, A.Montoya, I.Ul-Haq" <fmamadbe@abo.fi>
License: MIT License
Project-URL: Homepage, https://github.com/EDISS-intake2-team4/rots-py
Keywords: rots,gene,ranking
Classifier: License :: OSI Approved :: MIT License
Classifier: Programming Language :: Python
Classifier: Programming Language :: Python :: 3
Requires-Python: >=3.8
License-File: LICENSE
Requires-Dist: scikit-learn >=1.2.0
Requires-Dist: seaborn >=0.12.2
Requires-Dist: openpyxl >=3.1.2
Requires-Dist: numba >=0.56.4
Requires-Dist: tqdm >=4.64.1
Requires-Dist: numpy >=1.23.4
Requires-Dist: pandas >=1.5.3
Requires-Dist: matplotlib >=3.6.3
Requires-Dist: Cython >=3.0.4
